mimesniff/__init__.py
mimesniff/mimesniff.py
mimesniff-1.1.1.dist-info/LICENSE
mimesniff-1.1.1.dist-info/METADATA
mimesniff-1.1.1.dist-info/WHEEL
mimesniff-1.1.1.dist-info/top_level.txt
mimesniff-1.1.1.dist-info/RECORD
