Metadata-Version: 2.1
Name: mimesniff
Version: 1.1.1
Summary: Pure python mimesniff implementation of https://mimesniff.spec.whatwg.org
Home-page: https://github.com/corona10/mimesniff
Author: Dong-hee Na
Author-email: donghee.na92@gmail.com
License: UNKNOWN
Platform: UNKNOWN
Classifier: Programming Language :: Python :: 3.4
Classifier: Programming Language :: Python :: 3.5
Classifier: Programming Language :: Python :: 3.6
Classifier: Programming Language :: Python :: 3.7
Classifier: Programming Language :: Python :: 3.8
Classifier: Programming Language :: Python :: 3.9
Requires-Python: >=3.4
